navio/__init__.py
navio/__main__.py
navio/meta_builder.py
navio/builder/__init__.py
navio/builder/_nb.py
navio_builder-0.3.3.dist-info/LICENSE.txt
navio_builder-0.3.3.dist-info/METADATA
navio_builder-0.3.3.dist-info/WHEEL
navio_builder-0.3.3.dist-info/entry_points.txt
navio_builder-0.3.3.dist-info/top_level.txt
navio_builder-0.3.3.dist-info/RECORD
