Metadata-Version: 2.1
Name: navio-builder
Version: 0.3.3
Summary: Lightweight Python Build Tool
Home-page: https://github.com/navio-online/navio-builder/
Author: Navio Online OpenSource projects
Author-email: oss@navio.online
License: MIT License
Keywords: devops,build tool
Classifier: Development Status :: 4 - Beta
Classifier: Environment :: Console
Classifier: Intended Audience :: System Administrators
Classifier: Intended Audience :: Developers
Classifier: License :: OSI Approved :: MIT License
Classifier: Programming Language :: Python :: 2
Classifier: Programming Language :: Python :: 3
Classifier: Topic :: Software Development :: Build Tools
License-File: LICENSE.txt
Requires-Dist: sh
